vhacdx.cp38-win_amd64.pyd
vhacdx/VHACD.h
vhacdx/main.cpp
vhacdx-0.0.9.dist-info/LICENSE
vhacdx-0.0.9.dist-info/METADATA
vhacdx-0.0.9.dist-info/WHEEL
vhacdx-0.0.9.dist-info/top_level.txt
vhacdx-0.0.9.dist-info/RECORD
