Metadata-Version: 2.1
Name: vhacdx
Version: 0.0.9
Summary: Python bindings for VHACD
Author-email: Thomas Wolf <thomas@huggingface.co>
Project-URL: Homepage, https://github.com/trimesh/vhacdx
Requires-Python: >=3.7
License-File: LICENSE
Requires-Dist: numpy
Provides-Extra: test
Requires-Dist: pytest; extra == "test"
